{
    "SERVER_NAME":"bugacov.isi.edu",
    "DNS": "gpcr",
    "DATABASE_NAME":"rce",
    "USER_NAME":"sa",
    "DB_PASSWORD":"********",
    "DESTINATION_SERVER_NAME":"vm-dev-029.misd.isi.edu",
    "DESTINATION_USER_NAME":"gpcr1",
    "DESTINATION_PASSWORD":"*********",
    "EXTRACTS": [
         { "query_file" : "gpcr_tables/Status.sql",
	   "schema_name": "gpcr_new",
	   "table_name" : "Status",
	   "bulk_data_columns" : [],
	   "unique_key_columns": ["id"]
	 },
         { "query_file" : "gpcr_tables/Strain.sql",
	   "schema_name": "gpcr_new",
	   "table_name" : "Strain",
	   "bulk_data_columns" : [],
	   "unique_key_columns": ["id"]
	 },
         { "query_file" : "gpcr_tables/TagNterm.sql",
	   "schema_name": "gpcr_new",
	   "table_name" : "TagNterm",
	   "bulk_data_columns" : [],
	   "unique_key_columns": ["id"]
	 },
         { "query_file" : "gpcr_tables/TagCterm.sql",
	   "schema_name": "gpcr_new",
	   "table_name" : "TagCterm",
	   "bulk_data_columns" : [],
	   "unique_key_columns": ["id"]
	 },
         { "query_file" : "gpcr_tables/Truncations.sql",
	   "schema_name": "gpcr_new",
	   "table_name" : "Truncations",
	   "bulk_data_columns" : [],
	   "unique_key_columns": ["id"]
	 },
         { "query_file" : "gpcr_tables/Vector.sql",
	   "schema_name": "gpcr_new",
	   "table_name" : "Vector",
	   "bulk_data_columns" : [],
	   "unique_key_columns": ["id"]
	 },
         { "query_file" : "gpcr_tables/Host.sql",
	   "schema_name": "gpcr_new",
	   "table_name" : "Host",
	   "bulk_data_columns" : [],
	   "unique_key_columns": ["id"]
	 },
         { "query_file" : "gpcr_tables/Insertion.sql",
	   "schema_name": "gpcr_new",
	   "table_name" : "Insertion",
	   "bulk_data_columns" : [],
	   "unique_key_columns": ["id"]
	 },
         { "query_file" : "gpcr_tables/CleavageSite.sql",
	   "schema_name": "gpcr_new",
	   "table_name" : "CleavageSite",
	   "bulk_data_columns" : [],
	   "unique_key_columns": ["id"]
	 },
         { "query_file" : "gpcr_tables/Mutations.sql",
	   "schema_name": "gpcr_new",
	   "table_name" : "Mutations",
	   "bulk_data_columns" : [],
	   "unique_key_columns": ["id"]
	 },
         { "query_file" : "gpcr_tables/Organism.sql",
	   "schema_name": "gpcr_new",
	   "table_name" : "Organism",
	   "bulk_data_columns" : [],
	   "unique_key_columns": ["id"]
	 },
         { "query_file" : "gpcr_tables/UserList.sql",
	   "schema_name": "gpcr_new",
	   "table_name" : "UserList",
	   "bulk_data_columns" : [],
	   "unique_key_columns": ["id"]
	 },
         { "query_file" : "gpcr_tables/Target.sql",
	   "schema_name": "gpcr_new",
	   "table_name" : "Target",
	   "bulk_data_columns" : [],
	   "unique_key_columns": ["id"]
	 },
         { "query_file" : "gpcr_tables/Construct.sql",
	   "schema_name": "gpcr_new",
	   "table_name" : "Construct",
	   "bulk_data_columns" : [],
	   "unique_key_columns": ["id"]
	 },
         { "query_file" : "gpcr_tables/VirusProduction.sql",
	   "schema_name": "gpcr_new",
	   "table_name" : "VirusProduction",
	   "bulk_data_columns" : [],
	   "unique_key_columns": ["id"]
	 },
         { "query_file" : "gpcr_tables/BiomassProdBatch.sql",
	   "schema_name": "gpcr_new",
	   "table_name" : "BiomassProdBatch",
	   "bulk_data_columns" : [],
	   "unique_key_columns": ["id"]
	 },
         { "query_file" : "gpcr_tables/MembranePrep.sql",
	   "schema_name": "gpcr_new",
	   "table_name" : "MembranePrep",
	   "bulk_data_columns" : [],
	   "unique_key_columns": ["id"]
	 },
         { "query_file" : "gpcr_tables/ParentsOfMembranePreps.sql",
	   "schema_name": "gpcr_new",
	   "table_name" : "ParentsOfMembranePreps",
	   "bulk_data_columns" : [],
	   "unique_key_columns": ["id"]
	 }
    ]
}






